matiCalpackage/__init__.py
matiCalpackage/add.py
matiCalpackage/expo.py
matiCalpackage/subtract.py
matiCalpackage/extras/__init__.py
matiCalpackage/extras/divide.py
matiCalpackage/extras/multiply.py
matiCalpackageAlt-1.0.0.dist-info/METADATA
matiCalpackageAlt-1.0.0.dist-info/WHEEL
matiCalpackageAlt-1.0.0.dist-info/top_level.txt
matiCalpackageAlt-1.0.0.dist-info/RECORD
