Metadata-Version: 2.1
Name: matiCalpackageAlt
Version: 1.0.0
Summary: My first Python package
Author: Md Amjad Hossain
Author-email: <amjadkuet@gmail.com>
Keywords: python,simpleCalpackage
Classifier: Development Status :: 3 - Alpha
Classifier: Intended Audience :: Education
Classifier: Programming Language :: Python :: 2
Classifier: Programming Language :: Python :: 3
Classifier: Operating System :: MacOS :: MacOS X
Classifier: Operating System :: Microsoft :: Windows
